setup.cfg
setup.py
pgWitgets/__init__.py
pgWitgets/pgWitgets.py
pgWitgets.egg-info/PKG-INFO
pgWitgets.egg-info/SOURCES.txt
pgWitgets.egg-info/dependency_links.txt
pgWitgets.egg-info/not-zip-safe
pgWitgets.egg-info/top_level.txt