Metadata-Version: 2.1
Name: pgWitgets
Version: 1.2
Summary: Witgets for python pygame
Author-email: alekseybeldem@gmail.com
